MANIFEST.in
README
requirements.txt
setup.py
src/pyparser/__init__.py
src/pyparser/delimiter.py
src/pyparser/format.py
src/pyparser/regex.py
src/pyparser.egg-info/PKG-INFO
src/pyparser.egg-info/SOURCES.txt
src/pyparser.egg-info/dependency_links.txt
src/pyparser.egg-info/requires.txt
src/pyparser.egg-info/top_level.txt
src/pyparser.egg-info/zip-safe