Metadata-Version: 1.1
Name: pyparser
Version: 0.2
Summary: 
